carica/__init__.py
carica/carica.py
carica/exceptions.py
carica/typeChecking.py
carica/util.py
carica/interface/Serializable.py
carica/interface/__init__.py
carica/models/__init__.py
carica/models/dataclasses.py
carica/models/path.py
carica/models/timedelta.py
carica-1.3.5.dist-info/LICENSE
carica-1.3.5.dist-info/METADATA
carica-1.3.5.dist-info/WHEEL
carica-1.3.5.dist-info/top_level.txt
carica-1.3.5.dist-info/RECORD
