Metadata-Version: 2.1
Name: carica
Version: 1.3.5
Summary: Python module that populates variables from TOML config documents, and generates config documents from python variables.
Home-page: https://github.com/Trimatix/carica
Author: Jasper Law
Author-email: trimatix.music@gmail.com
Project-URL: Bug Tracker, https://github.com/Trimatix/carica/issues
Keywords: config,cfg,python,toml,generate,auto-generate,orm
Classifier: Programming Language :: Python :: 3.8
Classifier: License :: OSI Approved :: Apache Software License
Classifier: Operating System :: OS Independent
Requires-Python: >=3.8
License-File: LICENSE
Requires-Dist: tomlkit
Provides-Extra: test
Requires-Dist: pytest ; extra == 'test'
